setuptools_protobuf/__init__.py
setuptools_protobuf/py.typed
setuptools_protobuf-0.1.15.dist-info/licenses/LICENSE
setuptools_protobuf-0.1.15.dist-info/METADATA
setuptools_protobuf-0.1.15.dist-info/WHEEL
setuptools_protobuf-0.1.15.dist-info/entry_points.txt
setuptools_protobuf-0.1.15.dist-info/top_level.txt
setuptools_protobuf-0.1.15.dist-info/zip-safe
setuptools_protobuf-0.1.15.dist-info/RECORD
