Metadata-Version: 2.4
Name: setuptools-protobuf
Version: 0.1.15
Summary: Setuptools protobuf extension plugin
Author-email: Jelmer Vernooĳ <jelmer@jelmer.uk>
License: Apachev2
Project-URL: homepage, https://github.com/jelmer/setuptools-protobuf
Keywords: distutils,setuptools,protobuf
Classifier: Topic :: Software Development :: Version Control
Classifier: License :: OSI Approved :: Apache Software License
Classifier: Intended Audience :: Developers
Classifier: Programming Language :: Python :: 3.9
Classifier: Programming Language :: Python :: 3.10
Classifier: Programming Language :: Python :: 3.11
Classifier: Programming Language :: Python :: 3.12
Classifier: Programming Language :: Python :: 3.13
Classifier: Operating System :: POSIX
Classifier: Operating System :: MacOS :: MacOS X
Classifier: Operating System :: Microsoft :: Windows
Requires-Python: >=3.9
License-File: LICENSE
Requires-Dist: setuptools>=60.8
Requires-Dist: tomli>=1.2.1; python_version < "3.11"
Provides-Extra: mypy
Requires-Dist: mypy-protobuf; extra == "mypy"
Dynamic: license-file
